<annotation verified="no">
  <folder>1</folder>
  <filename>0140</filename>
  <path>/home/abby/Downloads/matlab/dataset/1/0140.jpg</path>
  <source>
    <database>Unknown</database>
  </source>
  <size>
    <width>411</width>
    <height>357</height>
    <depth>3</depth>
  </size>
  <segmented>0</segmented>
  <object>
    <name>robot</name>
    <pose>Unspecified</pose>
    <truncated>0</truncated>
    <Difficult>0</Difficult>
    <bndbox>
      <xmin>46</xmin>
      <ymin>130</ymin>
      <xmax>94</xmax>
      <ymax>200</ymax>
    </bndbox>
  </object>
  <object>
    <name>robot</name>
    <pose>Unspecified</pose>
    <truncated>0</truncated>
    <Difficult>0</Difficult>
    <bndbox>
      <xmin>168</xmin>
      <ymin>161</ymin>
      <xmax>253</xmax>
      <ymax>281</ymax>
    </bndbox>
  </object>
</annotation>
