<annotation verified="no">
  <folder>1</folder>
  <filename>0258</filename>
  <path>/home/abby/Downloads/matlab/dataset/1/0258.jpg</path>
  <source>
    <database>Unknown</database>
  </source>
  <size>
    <width>515</width>
    <height>367</height>
    <depth>3</depth>
  </size>
  <segmented>0</segmented>
  <object>
    <name>robot</name>
    <pose>Unspecified</pose>
    <truncated>0</truncated>
    <Difficult>0</Difficult>
    <bndbox>
      <xmin>54</xmin>
      <ymin>198</ymin>
      <xmax>145</xmax>
      <ymax>328</ymax>
    </bndbox>
  </object>
  <object>
    <name>robot</name>
    <pose>Unspecified</pose>
    <truncated>0</truncated>
    <Difficult>0</Difficult>
    <bndbox>
      <xmin>56</xmin>
      <ymin>116</ymin>
      <xmax>93</xmax>
      <ymax>170</ymax>
    </bndbox>
  </object>
  <object>
    <name>robot</name>
    <pose>Unspecified</pose>
    <truncated>0</truncated>
    <Difficult>0</Difficult>
    <bndbox>
      <xmin>408</xmin>
      <ymin>119</ymin>
      <xmax>468</xmax>
      <ymax>207</ymax>
    </bndbox>
  </object>
</annotation>
