<annotation verified="no">
  <folder>1</folder>
  <filename>0305</filename>
  <path>/home/abby/Downloads/matlab/dataset/1/0305.jpg</path>
  <source>
    <database>Unknown</database>
  </source>
  <size>
    <width>592</width>
    <height>444</height>
    <depth>3</depth>
  </size>
  <segmented>0</segmented>
  <object>
    <name>robot</name>
    <pose>Unspecified</pose>
    <truncated>0</truncated>
    <Difficult>0</Difficult>
    <bndbox>
      <xmin>38</xmin>
      <ymin>138</ymin>
      <xmax>100</xmax>
      <ymax>223</ymax>
    </bndbox>
  </object>
  <object>
    <name>robot</name>
    <pose>Unspecified</pose>
    <truncated>0</truncated>
    <Difficult>0</Difficult>
    <bndbox>
      <xmin>305</xmin>
      <ymin>160</ymin>
      <xmax>377</xmax>
      <ymax>270</ymax>
    </bndbox>
  </object>
  <object>
    <name>robot</name>
    <pose>Unspecified</pose>
    <truncated>0</truncated>
    <Difficult>0</Difficult>
    <bndbox>
      <xmin>473</xmin>
      <ymin>115</ymin>
      <xmax>515</xmax>
      <ymax>183</ymax>
    </bndbox>
  </object>
</annotation>
