<annotation verified="no">
  <folder>images</folder>
  <filename>img_1082</filename>
  <path>/home/abby/Downloads/youtube/images/img_1082.jpg</path>
  <source>
    <database>Unknown</database>
  </source>
  <size>
    <width>1280</width>
    <height>720</height>
    <depth>3</depth>
  </size>
  <segmented>0</segmented>
  <object>
    <name>robot</name>
    <pose>Unspecified</pose>
    <truncated>0</truncated>
    <Difficult>0</Difficult>
    <bndbox>
      <xmin>144</xmin>
      <ymin>288</ymin>
      <xmax>332</xmax>
      <ymax>540</ymax>
    </bndbox>
  </object>
  <object>
    <name>robot</name>
    <pose>Unspecified</pose>
    <truncated>0</truncated>
    <Difficult>0</Difficult>
    <bndbox>
      <xmin>446</xmin>
      <ymin>271</ymin>
      <xmax>599</xmax>
      <ymax>492</ymax>
    </bndbox>
  </object>
  <object>
    <name>robot</name>
    <pose>Unspecified</pose>
    <truncated>0</truncated>
    <Difficult>0</Difficult>
    <bndbox>
      <xmin>626</xmin>
      <ymin>245</ymin>
      <xmax>786</xmax>
      <ymax>492</ymax>
    </bndbox>
  </object>
  <object>
    <name>robot</name>
    <pose>Unspecified</pose>
    <truncated>0</truncated>
    <Difficult>0</Difficult>
    <bndbox>
      <xmin>950</xmin>
      <ymin>214</ymin>
      <xmax>1051</xmax>
      <ymax>371</ymax>
    </bndbox>
  </object>
</annotation>
