<annotation verified="no">
  <folder>images</folder>
  <filename>img_1279</filename>
  <path>/home/abby/Downloads/youtube/images/img_1279.jpg</path>
  <source>
    <database>Unknown</database>
  </source>
  <size>
    <width>1280</width>
    <height>720</height>
    <depth>3</depth>
  </size>
  <segmented>0</segmented>
  <object>
    <name>robot</name>
    <pose>Unspecified</pose>
    <truncated>0</truncated>
    <Difficult>0</Difficult>
    <bndbox>
      <xmin>372</xmin>
      <ymin>212</ymin>
      <xmax>477</xmax>
      <ymax>362</ymax>
    </bndbox>
  </object>
  <object>
    <name>robot</name>
    <pose>Unspecified</pose>
    <truncated>0</truncated>
    <Difficult>0</Difficult>
    <bndbox>
      <xmin>658</xmin>
      <ymin>245</ymin>
      <xmax>785</xmax>
      <ymax>427</ymax>
    </bndbox>
  </object>
  <object>
    <name>robot</name>
    <pose>Unspecified</pose>
    <truncated>0</truncated>
    <Difficult>0</Difficult>
    <bndbox>
      <xmin>896</xmin>
      <ymin>252</ymin>
      <xmax>1063</xmax>
      <ymax>521</ymax>
    </bndbox>
  </object>
  <object>
    <name>robot</name>
    <pose>Unspecified</pose>
    <truncated>0</truncated>
    <Difficult>0</Difficult>
    <bndbox>
      <xmin>1066</xmin>
      <ymin>272</ymin>
      <xmax>1230</xmax>
      <ymax>500</ymax>
    </bndbox>
  </object>
</annotation>
